Topsis_Ranking/topsis.py
TOPSIS_Gurleen_101903399-1.0.3.dist-info/LICENSE
TOPSIS_Gurleen_101903399-1.0.3.dist-info/METADATA
TOPSIS_Gurleen_101903399-1.0.3.dist-info/WHEEL
TOPSIS_Gurleen_101903399-1.0.3.dist-info/entry_points.txt
TOPSIS_Gurleen_101903399-1.0.3.dist-info/top_level.txt
TOPSIS_Gurleen_101903399-1.0.3.dist-info/RECORD
