Metadata-Version: 2.1
Name: TOPSIS-Gurleen-101903399
Version: 1.0.3
Summary: A Python package to get best alternative available using TOPSIS method.
Home-page: https://github.com/gurleen-kaur1313/topsis
Author: Gurleen Kaur
Author-email: gurleendhillonm1114@gmail.com
License: MIT
Platform: UNKNOWN
Classifier: Development Status :: 3 - Alpha
Classifier: Intended Audience :: Developers
Classifier: License :: OSI Approved :: MIT License
Classifier: Programming Language :: Python :: 3
Classifier: Programming Language :: Python :: 3.8
License-File: LICENSE
Requires-Dist: pandas
